traits_futures/__init__.py
traits_futures/api.py
traits_futures/background_call.py
traits_futures/background_iteration.py
traits_futures/background_progress.py
traits_futures/base_future.py
traits_futures/ets_event_loop.py
traits_futures/exception_handling.py
traits_futures/executor_states.py
traits_futures/future_states.py
traits_futures/i_event_loop.py
traits_futures/i_event_loop_helper.py
traits_futures/i_message_router.py
traits_futures/i_parallel_context.py
traits_futures/i_pingee.py
traits_futures/i_task_specification.py
traits_futures/multiprocessing_context.py
traits_futures/multiprocessing_router.py
traits_futures/multithreading_context.py
traits_futures/multithreading_router.py
traits_futures/traits_executor.py
traits_futures/version.py
traits_futures/wrappers.py
traits_futures/asyncio/__init__.py
traits_futures/asyncio/event_loop.py
traits_futures/asyncio/event_loop_helper.py
traits_futures/asyncio/pingee.py
traits_futures/asyncio/tests/__init__.py
traits_futures/asyncio/tests/test_asyncio_event_loop.py
traits_futures/asyncio/tests/test_event_loop_helper.py
traits_futures/asyncio/tests/test_pingee.py
traits_futures/qt/__init__.py
traits_futures/qt/event_loop.py
traits_futures/qt/event_loop_helper.py
traits_futures/qt/pingee.py
traits_futures/qt/tests/__init__.py
traits_futures/qt/tests/test_event_loop_helper.py
traits_futures/qt/tests/test_pingee.py
traits_futures/qt/tests/test_qt_event_loop.py
traits_futures/testing/__init__.py
traits_futures/testing/optional_dependencies.py
traits_futures/testing/test_assistant.py
traits_futures/tests/__init__.py
traits_futures/tests/background_call_tests.py
traits_futures/tests/background_iteration_tests.py
traits_futures/tests/background_progress_tests.py
traits_futures/tests/common_future_tests.py
traits_futures/tests/i_event_loop_helper_tests.py
traits_futures/tests/i_event_loop_tests.py
traits_futures/tests/i_message_router_tests.py
traits_futures/tests/i_pingee_tests.py
traits_futures/tests/test_api.py
traits_futures-0.3.1.dist-info/LICENSE.txt
traits_futures-0.3.1.dist-info/METADATA
traits_futures-0.3.1.dist-info/WHEEL
traits_futures-0.3.1.dist-info/entry_points.txt
traits_futures-0.3.1.dist-info/top_level.txt
traits_futures-0.3.1.dist-info/RECORD
