Metadata-Version: 2.1
Name: traits-futures
Version: 0.3.1
Summary: Patterns for reactive background tasks
Home-page: https://github.com/enthought/traits-futures
Author: Enthought
Author-email: info@enthought.com
License: BSD
Keywords: background concurrency futures gui traits traitsui
Platform: UNKNOWN
Classifier: Development Status :: 4 - Beta
Classifier: Intended Audience :: Developers
Classifier: License :: OSI Approved :: BSD License
Classifier: Operating System :: OS Independent
Classifier: Programming Language :: Python :: 3
Classifier: Programming Language :: Python :: 3.6
Classifier: Programming Language :: Python :: 3.7
Classifier: Programming Language :: Python :: 3.8
Classifier: Programming Language :: Python :: 3.9
Classifier: Programming Language :: Python :: 3.10
Requires-Python: >=3.6
License-File: LICENSE.txt
Requires-Dist: pyface
Requires-Dist: traits (>=6.2.0)
Provides-Extra: docs
Requires-Dist: enthought-sphinx-theme ; extra == 'docs'
Requires-Dist: sphinx (<4,>=3.5) ; extra == 'docs'
Provides-Extra: pyqt5
Requires-Dist: pyqt5 ; extra == 'pyqt5'
Provides-Extra: pyside2
Requires-Dist: pyside2 ; extra == 'pyside2'
